dsjson/__init__.py
dsjson/core.py
dsjson/version.py
dsjson-1.3.dist-info/licenses/LICENSE
dsjson-1.3.dist-info/METADATA
dsjson-1.3.dist-info/WHEEL
dsjson-1.3.dist-info/top_level.txt
dsjson-1.3.dist-info/RECORD
