Metadata-Version: 2.4
Name: dsjson
Version: 1.3
Summary: A Python package to convert tabular data and metadata into CDISC Dataset-JSON v1.1 format.
Author-email: Trinath Panda <pandatrinath1999@gmail.com>
License-Expression: MIT
Requires-Python: >=3.12
License-File: LICENSE
Requires-Dist: pandas>=1.5.0
Provides-Extra: test
Requires-Dist: pytest; extra == "test"
Requires-Dist: openpyxl; extra == "test"
Dynamic: license-file
